prestashop_webservice/__init__.py
prestashop_webservice/address.py
prestashop_webservice/base_model.py
prestashop_webservice/carrier.py
prestashop_webservice/client.py
prestashop_webservice/combination.py
prestashop_webservice/config.py
prestashop_webservice/country.py
prestashop_webservice/customer.py
prestashop_webservice/customer_message.py
prestashop_webservice/customer_thread.py
prestashop_webservice/image_product.py
prestashop_webservice/logger.py
prestashop_webservice/models.py
prestashop_webservice/order.py
prestashop_webservice/order_carrier.py
prestashop_webservice/order_detail.py
prestashop_webservice/order_history.py
prestashop_webservice/order_state.py
prestashop_webservice/params.py
prestashop_webservice/product.py
prestashop_webservice/py.typed
prestashop_webservice/state.py
prestashop_webservice-0.3.1.dist-info/licenses/LICENSE
prestashop_webservice-0.3.1.dist-info/METADATA
prestashop_webservice-0.3.1.dist-info/WHEEL
prestashop_webservice-0.3.1.dist-info/top_level.txt
prestashop_webservice-0.3.1.dist-info/RECORD
