Metadata-Version: 2.4
Name: prestashop-webservice
Version: 0.3.1
Summary: Webservice client for PrestaShop API
Author-email: Nestor Villa <nestorvilla@patitasco.com>, Manolo Corte <manolocorte@patitasco.com>
License: MIT License
Project-URL: Documentation, https://github.com/patitas-and-co/prestashop-webservice/blob/main/README.md
Project-URL: Repository, https://github.com/patitas-and-co/prestashop-webservice
Keywords: prestashop,api,client,webservice,rest
Requires-Python: >=3.12
License-File: LICENSE
Requires-Dist: httpx
Requires-Dist: cachetools
Requires-Dist: loguru
Requires-Dist: pre-commit
Provides-Extra: dev
Requires-Dist: pytest; extra == "dev"
Requires-Dist: pytest-cov; extra == "dev"
Requires-Dist: python-dotenv; extra == "dev"
Requires-Dist: ruff; extra == "dev"
Dynamic: license-file
